seqbank/__init__.py
seqbank/dfam.py
seqbank/exceptions.py
seqbank/io.py
seqbank/main.py
seqbank/refseq.py
seqbank/seqbank.py
seqbank/transform.py
seqbank/utils.py
seqbank-0.1.3.dist-info/METADATA
seqbank-0.1.3.dist-info/WHEEL
seqbank-0.1.3.dist-info/entry_points.txt
seqbank-0.1.3.dist-info/RECORD
