Metadata-Version: 2.1
Name: seqbank
Version: 0.1.3
Summary: A database to quickly read and write DNA sequence data in numerical form.
License: Apache-2.0
Author: Robert Turnbull
Author-email: robert.turnbull@unimelb.edu.au
Requires-Python: >=3.10,<3.13
Classifier: License :: OSI Approved :: Apache Software License
Classifier: Programming Language :: Python :: 3
Classifier: Programming Language :: Python :: 3.10
Classifier: Programming Language :: Python :: 3.11
Classifier: Programming Language :: Python :: 3.12
Requires-Dist: attrs (>=23.1.0)
Requires-Dist: biopython (>=1.81)
Requires-Dist: h5py (>=3.9.0)
Requires-Dist: joblib (>=1.3.2)
Requires-Dist: kaleido (==0.2.1)
Requires-Dist: numpy (>=1.22.0)
Requires-Dist: pandas (>=2.0.0)
Requires-Dist: plotly (>=5.0.0)
Requires-Dist: pyfastx (>=1.1.0)
Requires-Dist: requests (>=2.31.0)
Requires-Dist: rich (>=10.16.1)
Requires-Dist: speedict (>=0.3.11)
Requires-Dist: typer (>=0.4.0)
